{"cameraMode":{"drawMode":0,"name":"Shaded","section":"Shading Mode"},"sceneLighting":true,"audioPlay":false,"sceneViewState":{"m_AlwaysRefresh":false,"showFog":true,"showSkybox":true,"showFlares":true,"showImageEffects":true,"showParticleSystems":true,"showVisualEffectGraphs":true,"m_FxEnabled":true},"in2DMode":false,"pivot":{"x":363.3070068359375,"y":41.11040496826172,"z":498.6898193359375},"rotation":{"x":0.06925439834594727,"y":-0.0056785051710903648,"z":0.0003897023852914572,"w":0.9976021647453308},"size":101.98529052734375,"orthographic":false}